week4/decomposed.v
module decomposed(x,y,Ci,S,Co);
	input x,y,Ci;
	output S,Co;
	halfadd stage0 (x,y,S1,C1);
	halfadd stage1 (S1,Ci,C2,S);
	assign Co=(x&y)|(x&Ci)|(y&Ci);
endmodule

module halfadd(x,y,s,c);
	input x,y;
	output s,c;
	assign s=x^y;
	assign c=x&y;
endmodule

week4/decomposed_tb.v
`timescale 1ns/1ns
`include "decomposed.v"
module decomposed_tb();
reg x,y,Ci;
wire S1,C2,S,Co;
decomposed dfa(x,y,Ci,S,Co);
initial
begin
	$dumpfile("decomposed_tb.vcd");
	$dumpvars(0,decomposed_tb);
	
	x=1'b0;y=1'b0;Ci=1'b0;
	#20
	x=1'b0;y=1'b1;Ci=1'b0;
	#20
	x=1'b1;y=1'b0;Ci=1'b0;
	#20
	x=1'b1;y=1'b1;Ci=1'b0;
	#20
	x=1'b0;y=1'b0;Ci=1'b1;
	#20
	x=1'b0;y=1'b1;Ci=1'b1;
	#20
	x=1'b1;y=1'b0;Ci=1'b1;
	#20
	x=1'b1;y=1'b1;Ci=1'b1;
	#20
	
	
	$display("Test Complete");
end
endmodule

week4/decomposed_tb.vcd
$date
	Thu Sep 15 11:09:50 2022
$end
$version
	Icarus Verilog
$end
$timescale
	1ns
$end
$scope module decomposed_tb $end
$var wire 1 ! S $end
$var wire 1 " Co $end
$var reg 1 # Ci $end
$var reg 1 $ x $end
$var reg 1 % y $end
$scope module dfa $end
$var wire 1 # Ci $end
$var wire 1 " Co $end
$var wire 1 $ x $end
$var wire 1 % y $end
$var wire 1 & S1 $end
$var wire 1 ! S $end
$var wire 1 ' C2 $end
$var wire 1 ( C1 $end
$scope module stage0 $end
$var wire 1 ( c $end
$var wire 1 & s $end
$var wire 1 $ x $end
$var wire 1 % y $end
$upscope $end
$scope module stage1 $end
$var wire 1 ! c $end
$var wire 1 ' s $end
$var wire 1 & x $end
$var wire 1 # y $end
$upscope $end
$upscope $end
$upscope $end
$enddefinitions $end
#0
$dumpvars
0(
0'
0&
0%
0$
0#
0"
0!
$end
#20
1'
1&
1%
#40
0%
1$
#60
1"
0'
0&
1(
1%
#80
0"
1'
0(
1#
0%
0$
#100
1"
0'
1!
1&
1%
#120
0%
1$
#140
1'
0!
0&
1(
1%
