week4/fulladder.v
module fulladder(cin,x,y,sum,cout);
input cin,x,y;
output sum,cout;
assign sum = x^y^cin;
assign cout = (x&y)|(x&cin)|(y&cin);
endmodule

week4/fulladder_tb.v
`timescale 1ns/1ns
`include "fulladder.v"
module fulladder_tb();
reg x,y,cin;
wire sum,cout;
fulladder fa(x,y,cin,sum,cout);
initial
begin
	$dumpfile("fulladder_tb.vcd");
	$dumpvars(0,fulladder_tb);
	
	x=1'b0;y=1'b0;cin=1'b0;
	#20
	x=1'b0;y=1'b1;cin=1'b0;
	#20
	x=1'b1;y=1'b0;cin=1'b0;
	#20
	x=1'b1;y=1'b1;cin=1'b0;
	#20
	x=1'b0;y=1'b0;cin=1'b1;
	#20
	x=1'b0;y=1'b1;cin=1'b1;
	#20
	x=1'b1;y=1'b0;cin=1'b1;
	#20
	x=1'b1;y=1'b1;cin=1'b1;
	#20
	
	
	$display("Test Complete");
end
endmodule

week4/fulladder_tb.vcd
$date
	Thu Sep 15 10:10:53 2022
$end
$version
	Icarus Verilog
$end
$timescale
	1ns
$end
$scope module fulladder_tb $end
$var wire 1 ! sum $end
$var wire 1 " cout $end
$var reg 1 # cin $end
$var reg 1 $ x $end
$var reg 1 % y $end
$scope module fa $end
$var wire 1 $ cin $end
$var wire 1 " cout $end
$var wire 1 ! sum $end
$var wire 1 % x $end
$var wire 1 # y $end
$upscope $end
$upscope $end
$enddefinitions $end
#0
$dumpvars
0%
0$
0#
0"
0!
$end
#20
1!
1%
#40
1!
0%
1$
#60
1"
0!
1%
#80
0"
1!
1#
0%
0$
#100
1"
0!
1%
#120
0!
0%
1$
#140
1!
1%
