week3/lab3q2.v
module lab3q2(a,b,c,d,f);
input a,b,c,d;
output f;
assign p = ~(~(a|a)|~(b|b));
assign q = ~(d|~(b|b));
assign r = ~(~(c|c)|~(d|d));
assign f = ~(p|q|r);
endmodule

week3/lab3q2_tb.v
`timescale 1ns/1ns
`include "lab3q2.v"
module lab3q2_tb();
reg a,b,c,d;
wire f;
lab3q2 uup(a,b,c,d,f);
initial 
begin
	
	$dumpfile("lab3q2_tb.vcd");
	$dumpvars(0,lab3q2_tb);
	
	a=1'b0; b=1'b0; c=1'b0; d=1'b0;
	#20
	
	a=1'b0; b=1'b0; c=1'b0; d=1'b1;
	#20
	
	a=1'b0; b=1'b0; c=1'b1; d=1'b0;
	#20
	
	a=1'b0; b=1'b0; c=1'b1; d=1'b1;
	#20
	
	a=1'b0; b=1'b1; c=1'b0; d=1'b0;
	#20
	
	a=1'b0; b=1'b1; c=1'b0; d=1'b1;
	#20
	
	a=1'b0; b=1'b1; c=1'b1; d=1'b0;
	#20
	
	a=1'b0; b=1'b1; c=1'b1; d=1'b1;
	#20
	
	a=1'b1; b=1'b0; c=1'b0; d=1'b0;
	#20
	
	a=1'b1; b=1'b0; c=1'b0; d=1'b1;
	#20
	
	a=1'b1; b=1'b0; c=1'b1; d=1'b0;
	#20
	
	a=1'b1; b=1'b0; c=1'b1; d=1'b1;
	#20
	
	a=1'b1; b=1'b1; c=1'b0; d=1'b0;
	#20
	
	a=1'b1; b=1'b1; c=1'b0; d=1'b1;
	#20
	
	a=1'b1; b=1'b1; c=1'b1; d=1'b0;
	#20
	
	a=1'b1; b=1'b1; c=1'b1; d=1'b1;
	#20
	
	
	$display("Test Complete");
end

endmodule

week3/lab3q2_tb.vcd
$date
	Thu Sep  8 10:37:12 2022
$end
$version
	Icarus Verilog
$end
$timescale
	1ns
$end
$scope module lab3q2_tb $end
$var wire 1 ! f $end
$var reg 1 " a $end
$var reg 1 # b $end
$var reg 1 $ c $end
$var reg 1 % d $end
$scope module uup $end
$var wire 1 " a $end
$var wire 1 # b $end
$var wire 1 $ c $end
$var wire 1 % d $end
$var wire 1 ! f $end
$var wire 1 & p $end
$var wire 1 ' q $end
$var wire 1 ( r $end
$upscope $end
$upscope $end
$enddefinitions $end
#0
$dumpvars
0(
0'
0&
0%
0$
0#
0"
1!
$end
#20
1%
#40
0%
1$
#60
0!
1(
1%
#80
0(
1'
0%
0$
1#
#100
1!
0'
1%
#120
0!
1'
0%
1$
#140
1(
0'
1%
#160
1!
0(
0'
0%
0$
0#
1"
#180
1%
#200
0%
1$
#220
0!
1(
1%
#240
0(
1&
1'
0%
0$
1#
#260
0'
1%
#280
1'
0%
1$
#300
1(
0'
1%
